README.rst
setup.py
koch/__init__.py
koch/koch.py
koch/morse.py
koch.egg-info/PKG-INFO
koch.egg-info/SOURCES.txt
koch.egg-info/dependency_links.txt
koch.egg-info/entry_points.txt
koch.egg-info/requires.txt
koch.egg-info/top_level.txt