Metadata-Version: 1.1
Name: koch
Version: 0.0.3
Summary: Koch method Morse code training program
Home-page: https://github.com/casebeer/koch
Author: Christopher H. Casebeer
Author-email: christopher@chc.name
License: UNKNOWN
Platform: UNKNOWN
Classifier: Environment :: Console
Classifier: Topic :: Multimedia :: Sound/Audio
Classifier: Topic :: Communications :: Ham Radio
Classifier: Programming Language :: Python :: 2.7
